ahmadlib.py
ahmadlib-1.0.0.dist-info/METADATA
ahmadlib-1.0.0.dist-info/WHEEL
ahmadlib-1.0.0.dist-info/top_level.txt
ahmadlib-1.0.0.dist-info/RECORD
