Metadata-Version: 2.4
Name: ahmadlib
Version: 1.0.0
Summary: A fun library about Ahmad's legendary coding journey 🚀
Author: Ahmad Omer
Classifier: Programming Language :: Python :: 3
Classifier: Operating System :: OS Independent
Requires-Python: >=3.6
Dynamic: author
Dynamic: classifier
Dynamic: description
Dynamic: description-content-type
Dynamic: requires-python
Dynamic: summary
